bob/__init__.py
bob/admin.py
bob/api.py
bob/apps.py
bob/models.py
bob/tests.py
bob/urls.py
bob/utils.py
bob/views.py
bob/migrations/0001_initial.py
bob/migrations/0002_bobtasks.py
bob/migrations/__init__.py
bob/templates/bob/bobtask.html
bob/templates/bob/index.html
bob/templates/bob/login.html
django_bobgogo-1.1.dist-info/DESCRIPTION.rst
django_bobgogo-1.1.dist-info/METADATA
django_bobgogo-1.1.dist-info/RECORD
django_bobgogo-1.1.dist-info/WHEEL
django_bobgogo-1.1.dist-info/metadata.json
django_bobgogo-1.1.dist-info/top_level.txt
