Metadata-Version: 2.0
Name: django-bobgogo
Version: 1.1
Summary: A simple Django app to record tasks for you.
Home-page: https://github.com/liujinliu/bobgogo
Author: liujinliu
Author-email: 514371547@qq.com
License: UNKNOWN
Platform: UNKNOWN
Classifier: Environment :: Web Environment
Classifier: Framework :: Django
Classifier: Intended Audience :: Developers
Classifier: Operating System :: OS Independent
Classifier: Programming Language :: Python
Classifier: Programming Language :: Python :: 3.5
Classifier: Programming Language :: Python :: 3.6
